neobee/__init__.py
neobee/error.py
neobee/mqtt.py
neobee/neobee.py
neobee/net.py
neobee/shell.py
neobee/util.py
neobee-0.1.8.data/scripts/neobee
neobee-0.1.8.dist-info/METADATA
neobee-0.1.8.dist-info/WHEEL
neobee-0.1.8.dist-info/top_level.txt
neobee-0.1.8.dist-info/RECORD
