Metadata-Version: 2.1
Name: neobee
Version: 0.1.8
Summary: Condition Monitoring for Bee Hives
Home-page: https://github.com/FirstKlaas/neobee
Author: Klaas Nebuhr <FirstKlaas>
Author-email: klaas.nebuhr@gmail.com
License: UNKNOWN
Platform: UNKNOWN
Classifier: Programming Language :: Python :: 3
Classifier: License :: OSI Approved :: MIT License
Classifier: Operating System :: OS Independent
Requires-Python: >=3.6
